geodemora/__init__.py
geodemora/common.py
geodemora/geodemora.py
geodemora/spatial.py
geodemora/utils.py
geodemora-0.0.7.dist-info/LICENSE
geodemora-0.0.7.dist-info/METADATA
geodemora-0.0.7.dist-info/WHEEL
geodemora-0.0.7.dist-info/dependency_links.txt
geodemora-0.0.7.dist-info/top_level.txt
geodemora-0.0.7.dist-info/RECORD
