Metadata-Version: 2.1
Name: geodemora
Version: 0.0.7
Summary: A python package for interactive mapping
Home-page: https://github.com/ramendra1990/geodemora
Author: Ramendra Sahoo
Author-email: ramendrageo@gmail.com
License: MIT license
Keywords: geodemora
Platform: UNKNOWN
Classifier: Development Status :: 2 - Pre-Alpha
Classifier: Intended Audience :: Developers
Classifier: License :: OSI Approved :: MIT License
Classifier: Natural Language :: English
Classifier: Programming Language :: Python :: 3
Classifier: Programming Language :: Python :: 3.7
Classifier: Programming Language :: Python :: 3.8
Classifier: Programming Language :: Python :: 3.9
Classifier: Topic :: Scientific/Engineering :: GIS
Classifier: Intended Audience :: Science/Research
Classifier: Intended Audience :: Developers
Requires-Python: >=3.7
License-File: LICENSE
Requires-Dist: earthengine-api
Requires-Dist: folium
Requires-Dist: numpy
Requires-Dist: geopandas
Requires-Dist: ipyleaflet
Requires-Dist: pyshp
Requires-Dist: rasterio
